MIPS_Single_Cycle/ALU.v
module ALU(
    // System Clock

    // User Interface
    input       [31:0]  SrcA,
    input       [31:0]  SrcB,
    input       [2:0]   ALUControl,
    output  reg [31:0]  ALUResult,
    output              Zero
);

    always @(*) begin
        case (ALUControl)
            3'b010 : begin
                ALUResult = SrcA + SrcB;
            end 
            3'b110 : begin
                ALUResult = SrcA - SrcB;
            end
            3'b000 : ALUResult = SrcA & SrcB;
            3'b001 : ALUResult = SrcA | SrcB;
            3'b111 : ALUResult = (SrcA < SrcB) ? 32'b1 : 32'b0;
            default: ;
        endcase
    end

    assign Zero = (ALUResult) ? 1'b0 : 1'b1;

endmodule

MIPS_Single_Cycle/ALU_Control_Unit.v
module ALU_Control_Unit(
    // System Clock

    // User Interface
    input       [5:0]   Funct,
    input       [1:0]   ALUOp,
    output  reg [2:0]   ALUControl
);

    always @(*) begin
        case (ALUOp)
            2'b00: ALUControl = 3'b010;
            2'b10: begin
                case (Funct)
                    6'b100000 : ALUControl = 3'b010;
                    6'b100010 : ALUControl = 3'b110;
                    6'b100100 : ALUControl = 3'b000;
                    6'b100101 : ALUControl = 3'b001;
                    6'b101010 : ALUControl = 3'b111;
                endcase
            end
            2'b01: ALUControl = 3'b110;
            default: ;
        endcase
    end


endmodule

Pipeline/Data_Memory.v
module Data_Memory(
    // System Clock
    input        clk,
    input        rst_n,

    // User Interface
    input           [31:0]  A,
    input           [31:0]  WD,
    input                   WE,

    output   reg    [31:0]  RD
);
    integer fd;
    reg [31:0]  DATA_MEM[84:0];
/*******************************************************************************
 *                                 Main Code
*******************************************************************************/

    initial begin
        fd = $fopen("./MEM_Data.txt", "w");
        #500
        $fclose(fd);
    end

    always @(*) begin
        RD = DATA_MEM[A];
    end

    always @(posedge clk) begin
        if (WE) begin
            DATA_MEM[A] <= WD;
            $fdisplay(fd,"The Write Address A is %h", A);
            $fdisplay(fd,"DATA_MEM[A] is %h", WD);
        end
    end

endmodule

MIPS_Single_Cycle/Imm_Sign_Extend.v
module Imm_Sign_Extend(
    // System Clock

    // User Interface
    input       [15:0]  Immediate,

    output      [31:0]  SignImm
);
    assign  SignImm = {{16{Immediate[15]}}, Immediate[15:0]};
endmodule

Single Cycle/Reg_File.v
module Reg_File (
    input               clk,
    input       [4:0]   A1,
    input       [4:0]   A2,
    input       [4:0]   A3,

    input               RegWrite,
    input       [31:0]  WD3,
    output      [31:0]  RD2,
    output      [31:0]  RD1

);
    // lw : load word instr [op(6bit) rs(5bit) rd(5bit) imm(16bit)]

    reg [31:0]  ROM [31:0];
    initial begin
        ROM[0] <= 32'b0;
        ROM[1] <= 32'b0;
        ROM[2] <= 32'b0;
        ROM[3] <= 32'b0;
        ROM[4] <= 32'b0;
        ROM[5] <= 32'b0;
        ROM[6] <= 32'b0;
        ROM[7] <= 32'b0;
        ROM[8] <= 32'b0;
        ROM[9] <= 32'b0;
        ROM[10] <= 32'b0;
        ROM[11] <= 32'b0;
        ROM[12] <= 32'b0;
        ROM[13] <= 32'b0;
        ROM[14] <= 32'b0;
        ROM[15] <= 32'b0;
    end


    assign RD1 = ROM[A1];
    assign RD2 = ROM[A2];
    // RegWrite is set to 1 when lw Instr is executed
    always @(posedge clk) begin
        if (RegWrite) begin
            // load word
            ROM[A3] <= WD3;
        end
    end
endmodule

MIPS_Single_Cycle/Control_Unit.v
module Control_Unit(
    // System Clock
    input        clk,
    input        rst_n,

    // User Interface
    output  reg [1:0]    ALUOp,
    output  reg     MemWrite,RegWrite,
    output  reg     RegDst,
    output  reg     MemtoReg,
    output  reg     ALUSrc,
    output  reg     Branch,
    output  reg     Jump,
    input   [5:0]   Opcode
);

always @(*) begin
    case (Opcode)
        // R type no Immediate Instruction
        6'b000000 : begin
            RegWrite = 1'b1;
            RegDst   = 1'b1;
            ALUSrc   = 1'b0;
            Branch   = 1'b0;
            MemWrite = 1'b0;
            MemtoReg = 1'b0;
            ALUOp    = 2'b10;
            Jump     = 1'b0;
        end
        // beq Instruction
        6'b000100 : begin
            RegWrite = 1'b0;
            RegDst   = 1'b0;    // dont care
            ALUSrc   = 1'b0;
            Branch   = 1'b1;
            MemWrite = 1'b0;
            MemtoReg = 1'b0;    // dont care
            ALUOp    = 2'b01;
            Jump     = 1'b0;
        end
        // sw Instruction
        6'b101011 : begin
            RegWrite = 1'b0;
            RegDst   = 1'b0;
            ALUSrc   = 1'b1;
            Branch   = 1'b0;
            MemWrite = 1'b1;
            MemtoReg = 1'b1;
            ALUOp    = 2'b00;
            Jump     = 1'b0;
        end
        // lw Instruction
        6'b100011 : begin
            RegWrite = 1'b1;
            RegDst   = 1'b0;
            ALUSrc   = 1'b1;
            Branch   = 1'b0;
            MemWrite = 1'b0;
            MemtoReg = 1'b1;
            ALUOp    = 2'b00;
            Jump     = 1'b0;
        end
        // addi Instruction
        6'b001000 : begin
            RegWrite = 1'b1;
            RegDst   = 1'b0;
            ALUSrc   = 1'b1;
            Branch   = 1'b0;
            MemWrite = 1'b0;
            MemtoReg = 1'b0;
            ALUOp    = 2'b00;
            Jump     = 1'b0;
        end
        // J type Instruction
        6'b000010 : begin
            RegWrite = 1'b0;
            RegDst   = 1'b0;
            ALUSrc   = 1'b0;
            Branch   = 1'b0;
            MemWrite = 1'b0;
            MemtoReg = 1'b0;
            ALUOp    = 2'b00;
            Jump     = 1'b1;
        end
        default: ;
    endcase
end

endmodule

MIPS_Single_Cycle/Instr_Memory.v
module Instr_Memory(
	//System Clock
    input   [31:0]  A,
    output  [31:0]  RD

	//User Interface
);

	reg [7:0] Instr_Reg [71:0];
	initial begin
		$readmemh("./memfile.dat",Instr_Reg,0,71);
	end
    assign RD = {{Instr_Reg[A]},{Instr_Reg[A+32'd1]},{Instr_Reg[A+32'd2]},{Instr_Reg[A+32'd3]}};

endmodule

Single Cycle/PC_Counter.v
module PC_Counter(
    // System Clock
    input        clk,
    input        rst_n,

    // User Interface
    input                   PCSrc,
    input                   Jump,
    input           [31:0]  SignImm,
    input           [25:0]  Jump_low_26Bit,
    output   reg    [31:0]  PC
);
    wire            [31:0] PC_Next;
    wire            [31:0] PCPlus4;
    wire            [31:0] PCBranch;
    wire            [31:0] PCJump;


    assign PCPlus4  = PC + 32'd4;
    assign PCBranch = (SignImm << 2) + PCPlus4;
    assign PCJump   = {{PCPlus4[31:28]},{Jump_low_26Bit},2'b00}; 
    assign PC_Next  = Jump ? PCJump : (PCSrc ? PCBranch : PCPlus4);



    always @(posedge clk) begin
        if(~rst_n)begin
            PC <= 32'b0;
        end
        else 
            PC <= PC_Next;
    end

endmodule

Single Cycle/MIPS_Single_Cycle.v
module MIPS_Single_Cycle(
    // System Clock
    input        clk,
    input        rst_n

    // User Interface
    
);
    wire [31:0]     PC;
    wire [31:0]     Instr,ALUResult;
    wire [31:0]     ReadData,WriteData;
    wire [31:0]     SrcA,SrcB;
    wire            MemWrite,RegWrite;

    wire            RegDst,ALUSrc,MemtoReg;

    wire [4:0]      WriteReg;
    wire [31:0]     SignImm,RD2;
    wire [31:0]     WD3;

    wire            PCSrc,Branch,Zero;
    wire            Jump;

    wire [2:0]      ALUControl;
    wire [1:0]      ALUOp;


    assign PCSrc        = Branch & Zero;
    assign WriteReg     = RegDst ? Instr[15:11] : Instr[20:16];
    assign SrcB         = ALUSrc ? SignImm : RD2;
    assign WD3          = MemtoReg ? ReadData : ALUResult;
    assign WriteData    = RD2;

    PC_Counter u_PC_Counter(
        .clk(clk),
        .rst_n(rst_n),
        .PC(PC),
        .PCSrc(PCSrc),
        .Jump(Jump),
        .Jump_low_26Bit(Instr[25:0]),
        .SignImm(SignImm)
    );

    Instr_Memory u_Instr_Memory(
        .RD(Instr),
        .A(PC)
    );

    Control_Unit u_Control_Unit(
        .clk(clk),
        .rst_n(rst_n),
        .Opcode(Instr[31:26]),
        .MemWrite(MemWrite),
        .RegWrite(RegWrite),
        .RegDst(RegDst),
        .ALUSrc(ALUSrc),
        .MemtoReg(MemtoReg),
        .ALUOp(ALUOp),
        .Jump(Jump),
        .Branch(Branch)
    );

    Reg_File u_Reg_File(
        .clk(clk),
        .A1(Instr[25:21]),
        .RD1(SrcA),
        .A2(Instr[20:16]),
        .RD2(RD2),
        .A3(WriteReg),
        .RegWrite(RegWrite),
        .WD3(WD3)
    );

    Imm_Sign_Extend u_Imm_Sign_Extend(
        .Immediate(Instr[15:0]),
        .SignImm(SignImm)
    );

    Data_Memory u_Data_Memory(
        .clk(clk),
        .rst_n(rst_n),

        .A(ALUResult),
        .RD(ReadData),
        .WE(MemWrite),
        .WD(WriteData)
    );

    ALU_Control_Unit u_ALU_Control_Unit(
        .Funct(Instr[5:0]),
        .ALUOp(ALUOp),
        .ALUControl(ALUControl)
    );

    ALU u_ALU(
        .SrcA(SrcA),
        .SrcB(SrcB),
        .ALUControl(ALUControl),
        .ALUResult(ALUResult),
        .Zero(Zero)
    );

endmodule

MIPS_Single_Cycle/tb_MIPS_Single_Cycle.v
`timescale 1ps/1ps
`include "ALU_Control_Unit.v"
`include "ALU.v"
`include "Control_Unit.v"
`include "Data_Memory.v"
`include "Imm_Sign_Extend.v"
`include "Instr_Memory.v"
`include "MIPS_Single_Cycle.v"
`include "PC_Counter.v"
`include "Reg_File.v"

module tb_MIPS_Single_Cycle();

reg clk,rst_n;
reg [31:0] cnt;

initial
begin            
    $dumpfile("MIPS_wave.vcd");        
    $dumpvars(0, tb_MIPS_Single_Cycle);    
end

initial begin
    clk <= 1'b0;
    rst_n <= 1'b0;
    cnt <= 32'b0;

    #10
    clk <= 1'b1;

    #10
    clk <= 1'b0;
    rst_n <= 1'b1;

    forever begin
        #10 clk <= ~clk;
    end

end

always @(negedge clk) begin
    cnt <= cnt + 1'b1;
    if (cnt >= 17) begin
        $stop;
    end
end


MIPS_Single_Cycle u_MIPS_Single_Cycle(
    .clk(clk),
    .rst_n(rst_n)
);

endmodule

MIPS_Single_Cycle/MIPS_wave.vcd
$date
	Mon Nov 28 19:52:59 2022
$end
$version
	Icarus Verilog
$end
$timescale
	1ps
$end
$scope module tb_MIPS_Single_Cycle $end
$var reg 1 ! clk $end
$var reg 32 " cnt [31:0] $end
$var reg 1 # rst_n $end
$scope module u_MIPS_Single_Cycle $end
$var wire 1 $ PCSrc $end
$var wire 32 % WriteData [31:0] $end
$var wire 1 ! clk $end
$var wire 1 # rst_n $end
$var wire 1 & Zero $end
$var wire 5 ' WriteReg [4:0] $end
$var wire 32 ( WD3 [31:0] $end
$var wire 32 ) SrcB [31:0] $end
$var wire 32 * SrcA [31:0] $end
$var wire 32 + SignImm [31:0] $end
$var wire 1 , RegWrite $end
$var wire 1 - RegDst $end
$var wire 32 . ReadData [31:0] $end
$var wire 32 / RD2 [31:0] $end
$var wire 32 0 PC [31:0] $end
$var wire 1 1 MemtoReg $end
$var wire 1 2 MemWrite $end
$var wire 1 3 Jump $end
$var wire 32 4 Instr [31:0] $end
$var wire 1 5 Branch $end
$var wire 1 6 ALUSrc $end
$var wire 32 7 ALUResult [31:0] $end
$var wire 2 8 ALUOp [1:0] $end
$var wire 3 9 ALUControl [2:0] $end
$scope module u_ALU $end
$var wire 32 : SrcB [31:0] $end
$var wire 1 & Zero $end
$var wire 32 ; SrcA [31:0] $end
$var wire 3 < ALUControl [2:0] $end
$var reg 32 = ALUResult [31:0] $end
$upscope $end
$scope module u_ALU_Control_Unit $end
$var wire 6 > Funct [5:0] $end
$var wire 2 ? ALUOp [1:0] $end
$var reg 3 @ ALUControl [2:0] $end
$upscope $end
$scope module u_Control_Unit $end
$var wire 6 A Opcode [5:0] $end
$var wire 1 ! clk $end
$var wire 1 # rst_n $end
$var reg 2 B ALUOp [1:0] $end
$var reg 1 6 ALUSrc $end
$var reg 1 5 Branch $end
$var reg 1 3 Jump $end
$var reg 1 2 MemWrite $end
$var reg 1 1 MemtoReg $end
$var reg 1 - RegDst $end
$var reg 1 , RegWrite $end
$upscope $end
$scope module u_Data_Memory $end
$var wire 32 C A [31:0] $end
$var wire 32 D WD [31:0] $end
$var wire 1 2 WE $end
$var wire 1 ! clk $end
$var wire 1 # rst_n $end
$var reg 32 E RD [31:0] $end
$var integer 32 F fd [31:0] $end
$upscope $end
$scope module u_Imm_Sign_Extend $end
$var wire 16 G Immediate [15:0] $end
$var wire 32 H SignImm [31:0] $end
$upscope $end
$scope module u_Instr_Memory $end
$var wire 32 I RD [31:0] $end
$var wire 32 J A [31:0] $end
$upscope $end
$scope module u_PC_Counter $end
$var wire 1 3 Jump $end
$var wire 26 K Jump_low_26Bit [25:0] $end
$var wire 1 $ PCSrc $end
$var wire 32 L SignImm [31:0] $end
$var wire 1 ! clk $end
$var wire 1 # rst_n $end
$var wire 32 M PC_Next [31:0] $end
$var wire 32 N PCPlus4 [31:0] $end
$var wire 32 O PCJump [31:0] $end
$var wire 32 P PCBranch [31:0] $end
$var reg 32 Q PC [31:0] $end
$upscope $end
$scope module u_Reg_File $end
$var wire 5 R A1 [4:0] $end
$var wire 5 S A2 [4:0] $end
$var wire 5 T A3 [4:0] $end
$var wire 32 U RD1 [31:0] $end
$var wire 32 V RD2 [31:0] $end
$var wire 1 , RegWrite $end
$var wire 32 W WD3 [31:0] $end
$var wire 1 ! clk $end
$upscope $end
$upscope $end
$upscope $end
$enddefinitions $end
$comment Show the parameter values. $end
$dumpall
$end
#0
$dumpvars
bx W
bx V
bx U
bx T
bx S
bx R
bx Q
bx P
bx00 O
bx N
bx M
bx L
bx K
bx J
bx I
bx H
bx G
b10000000000000000000000000000011 F
bx E
bx D
bx C
bx B
bx A
bx @
bx ?
bx >
bx =
bx <
bx ;
bx :
bx 9
bx 8
bx 7
x6
x5
bx 4
x3
x2
x1
bx 0
bx /
bx .
x-
x,
bx +
bx *
bx )
bx (
bx '
x&
bx %
x$
0#
b1 "
0!
$end
#10
b0xxxxxxxxxxxxxxxxxxxxxxxxxx00 O
b100 N
b0 0
b0 J
b0 Q
1!
#20
b10 "
1#
0!
#30
bx00 O
bx N
bx 0
bx J
bx Q
1!
#40
b11 "
0!
#50
1!
#60
b100 "
0!
#70
1!
#80
b101 "
0!
#90
1!
#100
b110 "
0!
#110
1!
#120
b111 "
0!
#130
1!
#140
b1000 "
0!
#150
1!
#160
b1001 "
0!
#170
1!
#180
b1010 "
0!
#190
1!
#200
b1011 "
0!
#210
1!
#220
b1100 "
0!
#230
1!
#240
b1101 "
0!
#250
1!
#260
b1110 "
0!
#270
1!
#280
b1111 "
0!
#290
1!
#300
b10000 "
0!
#310
1!
#320
b10001 "
0!
